Workbook
Name Slicer_Category: #N/A
Name Slicer_Customer_Segment: #N/A
Name Slicer_Region: #N/A
Name Slicer_YEAR: #N/A

Sheet superstore_sales_dataset1
A1: Order ID | B1: Order Date | C1: Ship Date | D1: Ship Mode | E1: Customer Segment | F1: Region | G1: Category | H1: Sub-Category | I1: Sales | J1: Quantity | K1: Discount | L1: Profit
A2: ORD-1001 | B2: 45064 | C2: 45068 | D2: Same Day | E2: Corporate | F2: South | G2: Technology | H2: Accessories | I2: 387.05 | J2: 1 | K2: 0 | L2: 31.55
A3: ORD-1002 | B3: 44974 | C3: 44980 | D3: First Class | E3: Consumer | F3: West | G3: Office Supplies | H3: Paper | I3: 784.1 | J3: 4 | K3: 0 | L3: 69.33
A4: ORD-1003 | B4: 45210 | C4: 45211 | D4: Standard Class | E4: Corporate | F4: East | G4: Technology | H4: Accessories | I4: 172.87 | J4: 6 | K4: 0.2 | L4: -5.14
A5: ORD-1004 | B5: 44989 | C5: 44994 | D5: Second Class | E5: Consumer | F5: West | G5: Furniture | H5: Chairs | I5: 347.03 | J5: 4 | K5: 0.3 | L5: -39.84
A6: ORD-1005 | B6: 44975 | C6: 44981 | D6: First Class | E6: Corporate | F6: Central | G6: Technology | H6: Phones | I6: 40.17 | J6: 9 | K6: 0.1 | L6: 30.54
A7: ORD-1006 | B7: 45097 | C7: 45102 | D7: Second Class | E7: Consumer | F7: Central | G7: Office Supplies | H7: Storage | I7: 939.78 | J7: 3 | K7: 0.1 | L7: -7.27
A8: ORD-1007 | B8: 45122 | C8: 45124 | D8: First Class | E8: Home Office | F8: Central | G8: Technology | H8: Machines | I8: 199.74 | J8: 1 | K8: 0.3 | L8: -17.13
A9: ORD-1008 | B9: 44963 | C9: 44964 | D9: Standard Class | E9: Corporate | F9: Central | G9: Office Supplies | H9: Binders | I9: 26.92 | J9: 4 | K9: 0 | L9: 3.08
A10: ORD-1009 | B10: 45226 | C10: 45227 | D10: Second Class | E10: Corporate | F10: West | G10: Technology | H10: Phones | I10: 619.62 | J10: 10 | K10: 0.1 | L10: -16.73
A11: ORD-1010 | B11: 45068 | C11: 45072 | D11: Same Day | E11: Corporate | F11: South | G11: Furniture | H11: Bookcases | I11: 974.28 | J11: 7 | K11: 0.2 | L11: -85.5
A12: ORD-1011 | B12: 45138 | C12: 45142 | D12: Second Class | E12: Consumer | F12: West | G12: Furniture | H12: Tables | I12: 789.47 | J12: 5 | K12: 0.2 | L12: -72.17
A13: ORD-1012 | B13: 45076 | C13: 45079 | D13: Same Day | E13: Corporate | F13: East | G13: Technology | H13: Machines | I13: 983.57 | J13: 5 | K13: 0 | L13: 81.61
... A501: ORD-1500 | B501: 45232 | C501: 45237 | D501: Same Day | E501: Consumer | F501: Central | G501: Office Supplies | H501: Paper | I501: 913.6 | J501: 5 | K501: 0.1 | L501: 23.17

Sheet cleaned dataset
A1: Order ID | B1: Order Date | C1: Shipped date | D1: Days | E1: Ship Mode | F1: Order Month | G1: YEAR | H1: Quarter | I1: Customer Segment | J1: Region | K1: Category | L1: Sub-Category | M1: Sales | N1: Quantity | O1: Discount | P1: Profit | Q1: Profit Margin | R1: profit Status | S1: Discount Band | T1: Shipping Performance
A2: ORD-1001 | B2: 45064 | C2: 45068 | D2: =Table1[[#This Row],[Shipped date]]-Table1[[#This Row],[Order Date]] -> 4 | E2: Same Day | F2: =TEXT(Table1[[#This Row],[Order Date]],"MMMM") -> May | G2: =YEAR(B2) -> 2023 | H2: ="Q" &ROUNDUP(MONTH(B2)/3,0) -> Q2 | I2: Corporate | J2: South | K2: Technology | L2: Accessories | M2: 387.05 | N2: 1 | O2: 0 | P2: 31.55 | Q2: =Table1[[#This Row],[Profit]]/Table1[[#This Row],[Sales]] -> 0.081514016 | R2: =IF(Table1[[#This Row],[Profit Margin]]>0,"profit","loss") -> profit | S2: =IF(Table1[[#This Row],[Discount]]=0,"No Discount",IF(Table1[[#This Row],[Discount]]<=0.2,"low",IF(Table1[[#This Row],[Discount]]<=0.3,"medium","high"))) -> No Discount | T2: =IF(Table1[[#This Row],[Days]]<=2,"faster",IF(Table1[[#This Row],[Days]]<=4,"Normal","slow")) -> Normal
A3: ORD-1002 | B3: 44974 | C3: 44980 | D3: =Table1[[#This Row],[Shipped date]]-Table1[[#This Row],[Order Date]] -> 6 | E3: Same Day | F3: =TEXT(Table1[[#This Row],[Order Date]],"MMMM") -> February | G3: =YEAR(B3) -> 2023 | H3: ="Q" &ROUNDUP(MONTH(B3)/3,0) -> Q1 | I3: Consumer | J3: West | K3: Office Supplies | L3: Paper | M3: 784.1 | N3: 4 | O3: 0 | P3: 69.33 | Q3: =Table1[[#This Row],[Profit]]/Table1[[#This Row],[Sales]] -> 0.088419844 | R3: =IF(Table1[[#This Row],[Profit Margin]]>0,"profit","loss") -> profit | S3: =IF(Table1[[#This Row],[Discount]]=0,"No Discount",IF(Table1[[#This Row],[Discount]]<=0.2,"low",IF(Table1[[#This Row],[Discount]]<=0.3,"medium","high"))) -> No Discount | T3: =IF(Table1[[#This Row],[Days]]<=2,"faster",IF(Table1[[#This Row],[Days]]<=4,"Normal","slow")) -> slow
A4: ORD-1003 | B4: 45210 | C4: 45211 | D4: =Table1[[#This Row],[Shipped date]]-Table1[[#This Row],[Order Date]] -> 1 | E4: First Class | F4: =TEXT(Table1[[#This Row],[Order Date]],"MMMM") -> October | G4: =YEAR(B4) -> 2023 | H4: ="Q" &ROUNDUP(MONTH(B4)/3,0) -> Q4 | I4: Corporate | J4: East | K4: Technology | L4: Accessories | M4: 172.87 | N4: 6 | O4: 0.2 | P4: -5.14 | Q4: =Table1[[#This Row],[Profit]]/Table1[[#This Row],[Sales]] -> -0.029733326 | R4: =IF(Table1[[#This Row],[Profit Margin]]>0,"profit","loss") -> loss | S4: =IF(Table1[[#This Row],[Discount]]=0,"No Discount",IF(Table1[[#This Row],[Discount]]<=0.2,"low",IF(Table1[[#This Row],[Discount]]<=0.3,"medium","high"))) -> low | T4: =IF(Table1[[#This Row],[Days]]<=2,"faster",IF(Table1[[#This Row],[Days]]<=4,"Normal","slow")) -> faster
A5: ORD-1004 | B5: 44989 | C5: 44994 | D5: =Table1[[#This Row],[Shipped date]]-Table1[[#This Row],[Order Date]] -> 5 | E5: Standard Class | F5: =TEXT(Table1[[#This Row],[Order Date]],"MMMM") -> March | G5: =YEAR(B5) -> 2023 | H5: ="Q" &ROUNDUP(MONTH(B5)/3,0) -> Q1 | I5: Consumer | J5: West | K5: Furniture | L5: Chairs | M5: 347.03 | N5: 4 | O5: 0.3 | P5: -39.84 | Q5: =Table1[[#This Row],[Profit]]/Table1[[#This Row],[Sales]] -> -0.11480275 | R5: =IF(Table1[[#This Row],[Profit Margin]]>0,"profit","loss") -> loss | S5: =IF(Table1[[#This Row],[Discount]]=0,"No Discount",IF(Table1[[#This Row],[Discount]]<=0.2,"low",IF(Table1[[#This Row],[Discount]]<=0.3,"medium","high"))) -> medium | T5: =IF(Table1[[#This Row],[Days]]<=2,"faster",IF(Table1[[#This Row],[Days]]<=4,"Normal","slow")) -> slow | XFB5: Row Labels
A6: ORD-1005 | B6: 44975 | C6: 44981 | D6: =Table1[[#This Row],[Shipped date]]-Table1[[#This Row],[Order Date]] -> 6 | E6: Second Class | F6: =TEXT(Table1[[#This Row],[Order Date]],"MMMM") -> February | G6: =YEAR(B6) -> 2023 | H6: ="Q" &ROUNDUP(MONTH(B6)/3,0) -> Q1 | I6: Corporate | J6: Central | K6: Technology | L6: Phones | M6: 40.17 | N6: 9 | O6: 0.1 | P6: 30.54 | Q6: =Table1[[#This Row],[Profit]]/Table1[[#This Row],[Sales]] -> 0.76026886 | R6: =IF(Table1[[#This Row],[Profit Margin]]>0,"profit","loss") -> profit | S6: =IF(Table1[[#This Row],[Discount]]=0,"No Discount",IF(Table1[[#This Row],[Discount]]<=0.2,"low",IF(Table1[[#This Row],[Discount]]<=0.3,"medium","high"))) -> low | T6: =IF(Table1[[#This Row],[Days]]<=2,"faster",IF(Table1[[#This Row],[Days]]<=4,"Normal","slow")) -> slow | XFB6: First Class
A7: ORD-1006 | B7: 45097 | C7: 45102 | D7: =Table1[[#This Row],[Shipped date]]-Table1[[#This Row],[Order Date]] -> 5 | E7: First Class | F7: =TEXT(Table1[[#This Row],[Order Date]],"MMMM") -> June | G7: =YEAR(B7) -> 2023 | H7: ="Q" &ROUNDUP(MONTH(B7)/3,0) -> Q2 | I7: Consumer | J7: Central | K7: Office Supplies | L7: Storage | M7: 939.78 | N7: 3 | O7: 0.1 | P7: -7.27 | Q7: =Table1[[#This Row],[Profit]]/Table1[[#This Row],[Sales]] -> -0.0077358531 | R7: =IF(Table1[[#This Row],[Profit Margin]]>0,"profit","loss") -> loss | S7: =IF(Table1[[#This Row],[Discount]]=0,"No Discount",IF(Table1[[#This Row],[Discount]]<=0.2,"low",IF(Table1[[#This Row],[Discount]]<=0.3,"medium","high"))) -> low | T7: =IF(Table1[[#This Row],[Days]]<=2,"faster",IF(Table1[[#This Row],[Days]]<=4,"Normal","slow")) -> slow | XFB7: Same Day
A8: ORD-1007 | B8: 45122 | C8: 45124 | D8: =Table1[[#This Row],[Shipped date]]-Table1[[#This Row],[Order Date]] -> 2 | E8: Second Class | F8: =TEXT(Table1[[#This Row],[Order Date]],"MMMM") -> July | G8: =YEAR(B8) -> 2023 | H8: ="Q" &ROUNDUP(MONTH(B8)/3,0) -> Q3 | I8: Home Office | J8: Central | K8: Technology | L8: Machines | M8: 199.74 | N8: 1 | O8: 0.3 | P8: -17.13 | Q8: =Table1[[#This Row],[Profit]]/Table1[[#This Row],[Sales]] -> -0.08576149 | R8: =IF(Table1[[#This Row],[Profit Margin]]>0,"profit","loss") -> loss | S8: =IF(Table1[[#This Row],[Discount]]=0,"No Discount",IF(Table1[[#This Row],[Discount]]<=0.2,"low",IF(Table1[[#This Row],[Discount]]<=0.3,"medium","high"))) -> medium | T8: =IF(Table1[[#This Row],[Days]]<=2,"faster",IF(Table1[[#This Row],[Days]]<=4,"Normal","slow")) -> faster | XFB8: Second Class
A9: ORD-1008 | B9: 44963 | C9: 44964 | D9: =Table1[[#This Row],[Shipped date]]-Table1[[#This Row],[Order Date]] -> 1 | E9: First Class | F9: =TEXT(Table1[[#This Row],[Order Date]],"MMMM") -> February | G9: =YEAR(B9) -> 2023 | H9: ="Q" &ROUNDUP(MONTH(B9)/3,0) -> Q1 | I9: Corporate | J9: Central | K9: Office Supplies | L9: Binders | M9: 26.92 | N9: 4 | O9: 0 | P9: 3.08 | Q9: =Table1[[#This Row],[Profit]]/Table1[[#This Row],[Sales]] -> 0.11441308 | R9: =IF(Table1[[#This Row],[Profit Margin]]>0,"profit","loss") -> profit | S9: =IF(Table1[[#This Row],[Discount]]=0,"No Discount",IF(Table1[[#This Row],[Discount]]<=0.2,"low",IF(Table1[[#This Row],[Discount]]<=0.3,"medium","high"))) -> No Discount | T9: =IF(Table1[[#This Row],[Days]]<=2,"faster",IF(Table1[[#This Row],[Days]]<=4,"Normal","slow")) -> faster | XFB9: Standard Class
A10: ORD-1009 | B10: 45226 | C10: 45227 | D10: =Table1[[#This Row],[Shipped date]]-Table1[[#This Row],[Order Date]] -> 1 | E10: Standard Class | F10: =TEXT(Table1[[#This Row],[Order Date]],"MMMM") -> October | G10: =YEAR(B10) -> 2023 | H10: ="Q" &ROUNDUP(MONTH(B10)/3,0) -> Q4 | I10: Corporate | J10: West | K10: Technology | L10: Phones | M10: 619.62 | N10: 10 | O10: 0.1 | P10: -16.73 | Q10: =Table1[[#This Row],[Profit]]/Table1[[#This Row],[Sales]] -> -0.02700042 | R10: =IF(Table1[[#This Row],[Profit Margin]]>0,"profit","loss") -> loss | S10: =IF(Table1[[#This Row],[Discount]]=0,"No Discount",IF(Table1[[#This Row],[Discount]]<=0.2,"low",IF(Table1[[#This Row],[Discount]]<=0.3,"medium","high"))) -> low | T10: =IF(Table1[[#This Row],[Days]]<=2,"faster",IF(Table1[[#This Row],[Days]]<=4,"Normal","slow")) -> faster | XFB10: Grand Total
A11: ORD-1010 | B11: 45068 | C11: 45072 | D11: =Table1[[#This Row],[Shipped date]]-Table1[[#This Row],[Order Date]] -> 4 | E11: Second Class | F11: =TEXT(Table1[[#This Row],[Order Date]],"MMMM") -> May | G11: =YEAR(B11) -> 2023 | H11: ="Q" &ROUNDUP(MONTH(B11)/3,0) -> Q2 | I11: Corporate | J11: South | K11: Furniture | L11: Bookcases | M11: 974.28 | N11: 7 | O11: 0.2 | P11: -85.5 | Q11: =Table1[[#This Row],[Profit]]/Table1[[#This Row],[Sales]] -> -0.087757113 | R11: =IF(Table1[[#This Row],[Profit Margin]]>0,"profit","loss") -> loss | S11: =IF(Table1[[#This Row],[Discount]]=0,"No Discount",IF(Table1[[#This Row],[Discount]]<=0.2,"low",IF(Table1[[#This Row],[Discount]]<=0.3,"medium","high"))) -> low | T11: =IF(Table1[[#This Row],[Days]]<=2,"faster",IF(Table1[[#This Row],[Days]]<=4,"Normal","slow")) -> Normal
A12: ORD-1011 | B12: 45138 | C12: 45142 | D12: =Table1[[#This Row],[Shipped date]]-Table1[[#This Row],[Order Date]] -> 4 | E12: Same Day | F12: =TEXT(Table1[[#This Row],[Order Date]],"MMMM") -> July | G12: =YEAR(B12) -> 2023 | H12: ="Q" &ROUNDUP(MONTH(B12)/3,0) -> Q3 | I12: Consumer | J12: West | K12: Furniture | L12: Tables | M12: 789.47 | N12: 5 | O12: 0.2 | P12: -72.17 | Q12: =Table1[[#This Row],[Profit]]/Table1[[#This Row],[Sales]] -> -0.09141576 | R12: =IF(Table1[[#This Row],[Profit Margin]]>0,"profit","loss") -> loss | S12: =IF(Table1[[#This Row],[Discount]]=0,"No Discount",IF(Table1[[#This Row],[Discount]]<=0.2,"low",IF(Table1[[#This Row],[Discount]]<=0.3,"medium","high"))) -> low | T12: =IF(Table1[[#This Row],[Days]]<=2,"faster",IF(Table1[[#This Row],[Days]]<=4,"Normal","slow")) -> Normal
A13: ORD-1012 | B13: 45076 | C13: 45079 | D13: =Table1[[#This Row],[Shipped date]]-Table1[[#This Row],[Order Date]] -> 3 | E13: Second Class | F13: =TEXT(Table1[[#This Row],[Order Date]],"MMMM") -> May | G13: =YEAR(B13) -> 2023 | H13: ="Q" &ROUNDUP(MONTH(B13)/3,0) -> Q2 | I13: Corporate | J13: East | K13: Technology | L13: Machines | M13: 983.57 | N13: 5 | O13: 0 | P13: 81.61 | Q13: =Table1[[#This Row],[Profit]]/Table1[[#This Row],[Sales]] -> 0.082973251 | R13: =IF(Table1[[#This Row],[Profit Margin]]>0,"profit","loss") -> profit | S13: =IF(Table1[[#This Row],[Discount]]=0,"No Discount",IF(Table1[[#This Row],[Discount]]<=0.2,"low",IF(Table1[[#This Row],[Discount]]<=0.3,"medium","high"))) -> No Discount | T13: =IF(Table1[[#This Row],[Days]]<=2,"faster",IF(Table1[[#This Row],[Days]]<=4,"Normal","slow")) -> Normal
A14: ORD-1013 | B14: 45207 | C14: 45210 | D14: =Table1[[#This Row],[Shipped date]]-Table1[[#This Row],[Order Date]] -> 3 | E14: Same Day | F14: =TEXT(Table1[[#This Row],[Order Date]],"MMMM") -> October | G14: =YEAR(B14) -> 2023 | H14: ="Q" &ROUNDUP(MONTH(B14)/3,0) -> Q4 | I14: Home Office | J14: West | K14: Office Supplies | L14: Binders | M14: 615.39 | N14: 2 | O14: 0 | P14: 73.07 | Q14: =Table1[[#This Row],[Profit]]/Table1[[#This Row],[Sales]] -> 0.11873771 | R14: =IF(Table1[[#This Row],[Profit Margin]]>0,"profit","loss") -> profit | S14: =IF(Table1[[#This Row],[Discount]]=0,"No Discount",IF(Table1[[#This Row],[Discount]]<=0.2,"low",IF(Table1[[#This Row],[Discount]]<=0.3,"medium","high"))) -> No Discount | T14: =IF(Table1[[#This Row],[Days]]<=2,"faster",IF(Table1[[#This Row],[Days]]<=4,"Normal","slow")) -> Normal
A15: ORD-1014 | B15: 45231 | C15: 45233 | D15: =Table1[[#This Row],[Shipped date]]-Table1[[#This Row],[Order Date]] -> 2 | E15: Same Day | F15: =TEXT(Table1[[#This Row],[Order Date]],"MMMM") -> November | G15: =YEAR(B15) -> 2023 | H15: ="Q" &ROUNDUP(MONTH(B15)/3,0) -> Q4 | I15: Home Office | J15: West | K15: Office Supplies | L15: Storage | M15: 33 | N15: 5 | O15: 0 | P15: 50.89 | Q15: =Table1[[#This Row],[Profit]]/Table1[[#This Row],[Sales]] -> 1.5421212 | R15: =IF(Table1[[#This Row],[Profit Margin]]>0,"profit","loss") -> profit | S15: =IF(Table1[[#This Row],[Discount]]=0,"No Discount",IF(Table1[[#This Row],[Discount]]<=0.2,"low",IF(Table1[[#This Row],[Discount]]<=0.3,"medium","high"))) -> No Discount | T15: =IF(Table1[[#This Row],[Days]]<=2,"faster",IF(Table1[[#This Row],[Days]]<=4,"Normal","slow")) -> faster
A16: ORD-1015 | B16: 45002 | C16: 45003 | D16: =Table1[[#This Row],[Shipped date]]-Table1[[#This Row],[Order Date]] -> 1 | E16: First Class | F16: =TEXT(Table1[[#This Row],[Order Date]],"MMMM") -> March | G16: =YEAR(B16) -> 2023 | H16: ="Q" &ROUNDUP(MONTH(B16)/3,0) -> Q1 | I16: Home Office | J16: Central | K16: Furniture | L16: Tables | M16: 812.23 | N16: 2 | O16: 0 | P16: 62.34 | Q16: =Table1[[#This Row],[Profit]]/Table1[[#This Row],[Sales]] -> 0.076751659 | R16: =IF(Table1[[#This Row],[Profit Margin]]>0,"profit","loss") -> profit | S16: =IF(Table1[[#This Row],[Discount]]=0,"No Discount",IF(Table1[[#This Row],[Discount]]<=0.2,"low",IF(Table1[[#This Row],[Discount]]<=0.3,"medium","high"))) -> No Discount | T16: =IF(Table1[[#This Row],[Days]]<=2,"faster",IF(Table1[[#This Row],[Days]]<=4,"Normal","slow")) -> faster
A17: ORD-1016 | B17: 45131 | C17: 45133 | D17: =Table1[[#This Row],[Shipped date]]-Table1[[#This Row],[Order Date]] -> 2 | E17: Second Class | F17: =TEXT(Table1[[#This Row],[Order Date]],"MMMM") -> July | G17: =YEAR(B17) -> 2023 | H17: ="Q" &ROUNDUP(MONTH(B17)/3,0) -> Q3 | I17: Corporate | J17: East | K17: Furniture | L17: Tables | M17: 246.28 | N17: 4 | O17: 0.3 | P17: -38.45 | Q17: =Table1[[#This Row],[Profit]]/Table1[[#This Row],[Sales]] -> -0.15612311 | R17: =IF(Table1[[#This Row],[Profit Margin]]>0,"profit","loss") -> loss | S17: =IF(Table1[[#This Row],[Discount]]=0,"No Discount",IF(Table1[[#This Row],[Discount]]<=0.2,"low",IF(Table1[[#This Row],[Discount]]<=0.3,"medium","high"))) -> medium | T17: =IF(Table1[[#This Row],[Days]]<=2,"faster",IF(Table1[[#This Row],[Days]]<=4,"Normal","slow")) -> faster
A18: ORD-1017 | B18: 45229 | C18: 45232 | D18: =Table1[[#This Row],[Shipped date]]-Table1[[#This Row],[Order Date]] -> 3 | E18: First Class | F18: =TEXT(Table1[[#This Row],[Order Date]],"MMMM") -> October | G18: =YEAR(B18) -> 2023 | H18: ="Q" &ROUNDUP(MONTH(B18)/3,0) -> Q4 | I18: Consumer | J18: West | K18: Technology | L18: Machines | M18: 139.6 | N18: 9 | O18: 0 | P18: 52.28 | Q18: =Table1[[#This Row],[Profit]]/Table1[[#This Row],[Sales]] -> 0.37449857 | R18: =IF(Table1[[#This Row],[Profit Margin]]>0,"profit","loss") -> profit | S18: =IF(Table1[[#This Row],[Discount]]=0,"No Discount",IF(Table1[[#This Row],[Discount]]<=0.2,"low",IF(Table1[[#This Row],[Discount]]<=0.3,"medium","high"))) -> No Discount | T18: =IF(Table1[[#This Row],[Days]]<=2,"faster",IF(Table1[[#This Row],[Days]]<=4,"Normal","slow")) -> Normal
A19: ORD-1018 | B19: 45197 | C19: 45203 | D19: =Table1[[#This Row],[Shipped date]]-Table1[[#This Row],[Order Date]] -> 6 | E19: Same Day | F19: =TEXT(Table1[[#This Row],[Order Date]],"MMMM") -> September | G19: =YEAR(B19) -> 2023 | H19: ="Q" &ROUNDUP(MONTH(B19)/3,0) -> Q3 | I19: Home Office | J19: South | K19: Furniture | L19: Bookcases | M19: 189.9 | N19: 2 | O19: 0 | P19: 17.1 | Q19: =Table1[[#This Row],[Profit]]/Table1[[#This Row],[Sales]] -> 0.090047393 | R19: =IF(Table1[[#This Row],[Profit Margin]]>0,"profit","loss") -> profit | S19: =IF(Table1[[#This Row],[Discount]]=0,"No Discount",IF(Table1[[#This Row],[Discount]]<=0.2,"low",IF(Table1[[#This Row],[Discount]]<=0.3,"medium","high"))) -> No Discount | T19: =IF(Table1[[#This Row],[Days]]<=2,"faster",IF(Table1[[#This Row],[Days]]<=4,"Normal","slow")) -> slow
A20: ORD-1019 | B20: 44938 | C20: 44940 | D20: =Table1[[#This Row],[Shipped date]]-Table1[[#This Row],[Order Date]] -> 2 | E20: First Class | F20: =TEXT(Table1[[#This Row],[Order Date]],"MMMM") -> January | G20: =YEAR(B20) -> 2023 | H20: ="Q" &ROUNDUP(MONTH(B20)/3,0) -> Q1 | I20: Home Office | J20: West | K20: Office Supplies | L20: Paper | M20: 669.27 | N20: 5 | O20: 0.1 | P20: 9.76 | Q20: =Table1[[#This Row],[Profit]]/Table1[[#This Row],[Sales]] -> 0.014583053 | R20: =IF(Table1[[#This Row],[Profit Margin]]>0,"profit","loss") -> profit | S20: =IF(Table1[[#This Row],[Discount]]=0,"No Discount",IF(Table1[[#This Row],[Discount]]<=0.2,"low",IF(Table1[[#This Row],[Discount]]<=0.3,"medium","high"))) -> low | T20: =IF(Table1[[#This Row],[Days]]<=2,"faster",IF(Table1[[#This Row],[Days]]<=4,"Normal","slow")) -> faster
A21: ORD-1020 | B21: 45096 | C21: 45102 | D21: =Table1[[#This Row],[Shipped date]]-Table1[[#This Row],[Order Date]] -> 6 | E21: Standard Class | F21: =TEXT(Table1[[#This Row],[Order Date]],"MMMM") -> June | G21: =YEAR(B21) -> 2023 | H21: ="Q" &ROUNDUP(MONTH(B21)/3,0) -> Q2 | I21: Consumer | J21: Central | K21: Office Supplies | L21: Paper | M21: 223.78 | N21: 10 | O21: 0.3 | P21: -51.82 | Q21: =Table1[[#This Row],[Profit]]/Table1[[#This Row],[Sales]] -> -0.23156672 | R21: =IF(Table1[[#This Row],[Profit Margin]]>0,"profit","loss") -> loss | S21: =IF(Table1[[#This Row],[Discount]]=0,"No Discount",IF(Table1[[#This Row],[Discount]]<=0.2,"low",IF(Table1[[#This Row],[Discount]]<=0.3,"medium","high"))) -> medium | T21: =IF(Table1[[#This Row],[Days]]<=2,"faster",IF(Table1[[#This Row],[Days]]<=4,"Normal","slow")) -> slow
A22: ORD-1021 | B22: 45262 | C22: 45268 | D22: =Table1[[#This Row],[Shipped date]]-Table1[[#This Row],[Order Date]] -> 6 | E22: Standard Class | F22: =TEXT(Table1[[#This Row],[Order Date]],"MMMM") -> December | G22: =YEAR(B22) -> 2023 | H22: ="Q" &ROUNDUP(MONTH(B22)/3,0) -> Q4 | I22: Consumer | J22: Central | K22: Furniture | L22: Chairs | M22: 970.19 | N22: 5 | O22: 0.1 | P22: 11.48 | Q22: =Table1[[#This Row],[Profit]]/Table1[[#This Row],[Sales]] -> 0.011832734 | R22: =IF(Table1[[#This Row],[Profit Margin]]>0,"profit","loss") -> profit | S22: =IF(Table1[[#This Row],[Discount]]=0,"No Discount",IF(Table1[[#This Row],[Discount]]<=0.2,"low",IF(Table1[[#This Row],[Discount]]<=0.3,"medium","high"))) -> low | T22: =IF(Table1[[#This Row],[Days]]<=2,"faster",IF(Table1[[#This Row],[Days]]<=4,"Normal","slow")) -> slow
... A501: ORD-1500 | B501: 45232 | C501: 45237 | D501: =Table1[[#This Row],[Shipped date]]-Table1[[#This Row],[Order Date]] -> 5 | E501: First Class | F501: =TEXT(Table1[[#This Row],[Order Date]],"MMMM") -> November | G501: =YEAR(B501) -> 2023 | H501: ="Q" &ROUNDUP(MONTH(B501)/3,0) -> Q4 | I501: Consumer | J501: Central | K501: Office Supplies | L501: Paper | M501: 913.6 | N501: 5 | O501: 0.1 | P501: 23.17 | Q501: =Table1[[#This Row],[Profit]]/Table1[[#This Row],[Sales]] -> 0.025361208 | R501: =IF(Table1[[#This Row],[Profit Margin]]>0,"profit","loss") -> profit | S501: =IF(Table1[[#This Row],[Discount]]=0,"No Discount",IF(Table1[[#This Row],[Discount]]<=0.2,"low",IF(Table1[[#This Row],[Discount]]<=0.3,"medium","high"))) -> low | T501: =IF(Table1[[#This Row],[Days]]<=2,"faster",IF(Table1[[#This Row],[Days]]<=4,"Normal","slow")) -> slow
D502: =Table1[[#This Row],[Shipped date]]-Table1[[#This Row],[Order Date]] -> 0 | E502: Same Day | F502: =TEXT(Table1[[#This Row],[Order Date]],"MMMM") -> January | Q502: =Table1[[#This Row],[Profit]]/Table1[[#This Row],[Sales]] -> #DIV/0! | R502: =IF(Table1[[#This Row],[Profit Margin]]>0,"profit","loss") -> #DIV/0! | S502: =IF(Table1[[#This Row],[Discount]]=0,"No Discount",IF(Table1[[#This Row],[Discount]]<=0.2,"low",IF(Table1[[#This Row],[Discount]]<=0.3,"medium","high"))) -> No Discount | T502: =IF(Table1[[#This Row],[Days]]<=2,"faster",IF(Table1[[#This Row],[Days]]<=4,"Normal","slow")) -> faster

Sheet PIVOT TABLE
A2: Sales by category | E2: Sales by sub- category | I2: profit by sub- category | M2: sales trends
A3: Row Labels | B3: Sum of Sales | E3: Row Labels | F3: Sum of Sales | I3: Row Labels | J3: Sum of Profit | M3: Sum of Profit | N3: Column Labels
A4: Furniture | B4: 30924.56 | E4: Bookcases | F4: 13341.88 | I4: Tables | J4: -643.78 | M4: Row Labels | N4: 2023 | O4: Grand Total
A5: Grand Total | B5: 30924.56 | E5: Tables | F5: 10199.22 | I5: Bookcases | J5: -290.38 | M5: January | N5: -258.12 | O5: -258.12
E6: Chairs | F6: 7383.46 | I6: Chairs | J6: 122.8 | M6: February | N6: -109.19 | O6: -109.19
E7: Grand Total | F7: 30924.56 | I7: Grand Total | J7: -811.36 | M7: March | N7: -16.18 | O7: -16.18
M8: April | N8: 40.5 | O8: 40.5
M9: May | N9: 9.17 | O9: 9.17
E10: profit by region | I10: average discount | M10: June | N10: -170.18 | O10: -170.18
A11: profit by Category | E11: Row Labels | F11: Sum of Profit | I11: Row Labels | J11: Average of Discount | M11: July | N11: -49.17 | O11: -49.17
A12: Row Labels | B12: Sum of Profit | E12: Central | F12: -5.99 | I12: Furniture | J12: 0.14655172 | M12: August | N12: -199.38 | O12: -199.38
A13: Furniture | B13: -811.36 | E13: East | F13: -328.51 | I13: Grand Total | J13: 0.14655172 | M13: September | N13: -124.83 | O13: -124.83
A14: Grand Total | B14: -811.36 | E14: South | F14: -459.56 | M14: October | N14: 109.65 | O14: 109.65
E15: West | F15: -17.3 | M15: November | N15: -16.22 | O15: -16.22
E16: Grand Total | F16: -811.36 | M16: December | N16: -27.41 | O16: -27.41
M17: Grand Total | N17: -811.36 | O17: -811.36
A19: sales by region
A20: Row Labels | B20: Sum of Sales
A21: Central | B21: 3920.61
A22: East | B22: 9983.72
A23: South | B23: 10730.8
A24: West | B24: 6289.43
A25: Grand Total | B25: 30924.56
D29: total orders | F29: total proift | H29: average shipping dates
D30: Count of Order ID | F30: Sum of Profit | H30: Average of Days
D31: 58 | F31: -811.36 | H31: 4.3103448

Sheet KPIs Calculation
A3: Total Sales | B3: =GETPIVOTDATA("Sales",'PIVOT TABLE'!$E$3) -> 30924.56
A4: Total Profit | B4: =GETPIVOTDATA("Profit",'PIVOT TABLE'!$F$30) -> -811.36
A5: Total Orders | B5: =GETPIVOTDATA(" Order ID",'PIVOT TABLE'!$D$30) -> 58
A6: Average Discount | B6: =GETPIVOTDATA("Discount",'PIVOT TABLE'!$I$11) -> 0.14655172
A7: Average shipping days | B7: =GETPIVOTDATA("Days",'PIVOT TABLE'!$H$30) -> 4.3103448

Sheet superstore_sales_DASHBOARD
